odoo9_addon_donation_sale-9.0.1.0.0.99.dev11-py2.7-nspkg.pth
odoo9_addon_donation_sale-9.0.1.0.0.99.dev11.dist-info/METADATA
odoo9_addon_donation_sale-9.0.1.0.0.99.dev11.dist-info/RECORD
odoo9_addon_donation_sale-9.0.1.0.0.99.dev11.dist-info/WHEEL
odoo9_addon_donation_sale-9.0.1.0.0.99.dev11.dist-info/namespace_packages.txt
odoo9_addon_donation_sale-9.0.1.0.0.99.dev11.dist-info/top_level.txt
odoo_addons/donation_sale/README.rst
odoo_addons/donation_sale/__init__.py
odoo_addons/donation_sale/__openerp__.py
odoo_addons/donation_sale/data/cron.xml
odoo_addons/donation_sale/i18n/fr.po
odoo_addons/donation_sale/models/__init__.py
odoo_addons/donation_sale/models/donation_sale.py
odoo_addons/donation_sale/static/description/icon.png
odoo_addons/donation_sale/views/account_invoice.xml
odoo_addons/donation_sale/views/donation_tax.xml
odoo_addons/donation_sale/views/sale_order.xml
